{
	"miniprogramRoot": "miniprogram/",
	"cloudfunctionRoot": "cloudfunctions/",
	"setting": {
		"urlCheck": true,
		"es6": false,
		"enhance": true,
		"postcss": true,
		"preloadBackgroundData": false,
		"minified": true,
		"newFeature": true,
		"coverView": true,
		"nodeModules": true,
		"autoAudits": false,
		"showShadowRootInWxmlPanel": false,
		"scopeDataCheck": false,
		"uglifyFileName": true,
		"checkInvalidKey": true,
		"checkSiteMap": true,
		"uploadWithSourceMap": true,
		"compileHotReLoad": false,
		"babelSetting": {
			"ignore": [],
			"disablePlugins": [],
			"outputPath": ""
		},
		"bundle": false,
		"useIsolateContext": true,
		"useCompilerModule": true,
		"userConfirmedUseCompilerModuleSwitch": true,
		"useMultiFrameRuntime": true,
		"useApiHook": true,
		"packNpmManually": false,
		"packNpmRelationList": []
	},
	"appid": "wxf3f6462195815590",
	"projectname": "roundmatch",
	"libVersion": "2.13.0",
	"simulatorType": "wechat",
	"simulatorPluginLibVersion": {},
	"compileType": "miniprogram",
	"cloudfunctionTemplateRoot": "cloudfunctionTemplate",
	"condition": {
		"search": {
			"current": -1,
			"list": []
		},
		"conversation": {
			"current": -1,
			"list": []
		},
		"plugin": {
			"current": -1,
			"list": []
		},
		"game": {
			"list": []
		},
		"miniprogram": {
			"current": 0,
			"list": [
				{
					"id": -1,
					"name": "db guide",
					"pathName": "pages/databaseGuide/databaseGuide"
				}
			]
		}
	}
}